guichet/__init__.py
guichet/guichet.py
guichet-0.0.2.dist-info/METADATA
guichet-0.0.2.dist-info/WHEEL
guichet-0.0.2.dist-info/licenses/license
guichet-0.0.2.dist-info/RECORD
