Metadata-Version: 2.1
Name: guichet
Version: 0.0.2
Summary: Quickly create simple GUIs in Python
Project-URL: Homepage, https://github.com/ubalklen/guichet
Project-URL: Bug Tracker, https://github.com/ubalklen/guichet/issues
Author-email: ubalklen <42127323+ubalklen@users.noreply.github.com>
License-File: license
Requires-Dist: pydantic
Requires-Dist: pysimplegui
